djangoldp_application/__init__.py
djangoldp_application/admin.py
djangoldp_application/apps.py
djangoldp_application/djangoldp_urls.py
djangoldp_application/models.py
djangoldp_application/settings.py
djangoldp_application/views.py
djangoldp_application/migrations/0001_initial.py
djangoldp_application/migrations/0002_deployment.py
djangoldp_application/migrations/0003_application_api_url.py
djangoldp_application/migrations/0004_auto_20230328_1657.py
djangoldp_application/migrations/0005_auto_20230331_0850.py
djangoldp_application/migrations/0006_applicationservice.py
djangoldp_application/migrations/0007_auto_20230331_0857.py
djangoldp_application/migrations/0008_applicationnpm.py
djangoldp_application/migrations/0009_applicationgraphics.py
djangoldp_application/migrations/0010_auto_20230331_0921.py
djangoldp_application/migrations/0011_auto_20230512_1555.py
djangoldp_application/migrations/0012_auto_20230512_1556.py
djangoldp_application/migrations/0013_auto_20230512_1608.py
djangoldp_application/migrations/0014_auto_20230512_1613.py
djangoldp_application/migrations/__init__.py
djangoldp_application/templates/djangoldp_application/email.html
djangoldp_application-2.0.8.dist-info/METADATA
djangoldp_application-2.0.8.dist-info/WHEEL
djangoldp_application-2.0.8.dist-info/top_level.txt
djangoldp_application-2.0.8.dist-info/RECORD
