Metadata-Version: 2.1
Name: djangoldp-application
Version: 2.0.8
Summary: djangoldp application management package
Home-page: https://git.startinblox.com/applications/ontochain/application-registry
Author: Startin'blox
Author-email: jbaptiste@startinblox.com
License: MIT
Requires-Dist: djangoldp ~=3.0
Requires-Dist: djangoldp-branding
Requires-Dist: djangoldp-account ~=3.0
Requires-Dist: djangoldp-component
Requires-Dist: djangorestframework-yaml ~=2.0
